givemebib/__init__.py
givemebib/__main__.py
givemebib/functions.py
givemebib/givemebib.ini
givemebib/journal_abbreviations.dat
givemebib-1.0.2.dist-info/LICENSE
givemebib-1.0.2.dist-info/METADATA
givemebib-1.0.2.dist-info/WHEEL
givemebib-1.0.2.dist-info/entry_points.txt
givemebib-1.0.2.dist-info/top_level.txt
givemebib-1.0.2.dist-info/RECORD
