Metadata-Version: 2.1
Name: givemebib
Version: 1.0.2
Summary: Provides clean .bib files, with possible abbreviation of journal titles
Home-page: https://github.com/bgrosjea/givemebib
Author: Benoit Grosjean
Author-email: grosjean.benoit@gmail.com
License: UNKNOWN
Platform: UNKNOWN
Classifier: Programming Language :: Python :: 3
Classifier: License :: OSI Approved :: GNU General Public License v3 (GPLv3)
Classifier: Operating System :: OS Independent
Requires-Python: >=3.5.6
Requires-Dist: mechanize (>=0.4.5)
Requires-Dist: pdfminer.six (>=20200402)
Requires-Dist: PyPDF2 (>=1.26.0)
